duck_takes_flight/__init__.py
duck_takes_flight/cli.py
duck_takes_flight/client.py
duck_takes_flight/logging.py
duck_takes_flight/server.py
duck_takes_flight-0.3.0.dist-info/METADATA
duck_takes_flight-0.3.0.dist-info/WHEEL
duck_takes_flight-0.3.0.dist-info/entry_points.txt
duck_takes_flight-0.3.0.dist-info/top_level.txt
duck_takes_flight-0.3.0.dist-info/RECORD
