Metadata-Version: 2.4
Name: duck-takes-flight
Version: 0.3.0
Summary: A high-performance data streaming system using DuckDB and Apache Arrow Flight
Requires-Python: >=3.12
Requires-Dist: duckdb>=1.2.1
Requires-Dist: polars>=1.25.2
Requires-Dist: pyarrow>=19.0.1
